<?xml version='1.0' encoding='UTF-8'?>
<resources>
  <!--Property values-->
  <string name="BURST_NUMBER">Continue-opname nummer</string>
  <string name="STILL_CAPTURE_MODE">Statisch beeld modus</string>
  <string name="CONTINUOUS_SHOT__CONTINUOUS_SHOOTING_">Doorlopende opname (doorlopend opnemen)</string>
  <string name="AUTO_ISO">Auto Iso</string>
  <string name="ON">AAN</string>
  <string name="OFF">UIT</string>
  <string name="FLASH">Flitser</string>
  <string name="NORMAL_SYNCHRONIZATION">Normale synchronisatie</string>
  <string name="LONG_EXP._NR">Lang exp. NR</string>
  <string name="HIGH_ISO_NR">Hoog ISO NR</string>
  <string name="NORMAL">Normaal</string>
  <string name="EXPOSURE_DELAY_MODE">Belichting vertraging modus</string>
  <string name="LOCK">Vergrendel</string>
  <string name="SINGLE_SHOT__SINGLE_FRAME_SHOOTING_">Enkele opname (enkelvoudige beeld opnemen)</string>
  <string name="SELF_TIMER">Zelfontspanner</string>
  <string name="QUICK_RESPONSE_REMOTE">Quick-response afstandsbediening</string>
  <string name="2S_DELAYED_REMOTE">2sec vertraagde afstandsbediending</string>
  <string name="QUIET_SHOOTING">Stille opname</string>
  <string name="FLASH_PROHIBITED">Flitsen niet toegestaan</string>
  <string name="RED_EYE_REDUCTION">Rode-ogen correctie</string>
  <string name="SLOW_SYNCHRONIZATION">Trage synchronisatie</string>
  <string name="REAR_SYNCHRONIZATION">Eindflank synchronisatie</string>
  <string name="RED_EYE_REDUCTION_SLOW_SYNCHRONIZATION">Rode-ogen correctie trage synchronisatie </string>
  <string name="NOT_PERFORMED">Niet uitgevoerd</string>
  <string name="LOW">Laag</string>
  <string name="HIGH">Hoog</string>
  <string name="CENTER_WEIGHTED_METERING">Centrumgerichte meting</string>
  <string name="MULTI_PATTERN_METERING">Matrix meting</string>
  <string name="SPOT_METERING">Spotmeting</string>
  <string name="AUTO">Auto</string>
  <string name="DAYLIGHT">Daglicht</string>
  <string name="FLUORESCENT_">Fluorescerende</string>
  <string name="INCANDESCENT">Gloeiend</string>
  <string name="CLOUDY">Bewolkt</string>
  <string name="SHADE">Schaduw</string>
  <string name="CUSTOM">Custom</string>
  <string name="[A]_AF_SERVO_MODE_AUTOMATIC_SWITCHING">[AF-A] Automatische servo-AF</string>
  <string name="[S]_SINGLE_AF_SERVO">[AF-S] Enkelvoudige servo-AF</string>
  <string name="[M]_MANUAL_FOCUS">[MF] Handmatige scherpstelling</string>
  <string name="KELVIN">Kelvin</string>
  <string name="APPLICATION_MODE">Toepassingsmodus</string>
  <string name="WHITE_FLUORESCENT_LAMP">Witte fluorescentielamp</string>
  <string name="FLUORESCENT_LIGHT_TYPE">TL verlichting</string>
  <string name="ADOBE_RGB">Adobe RGB</string>
  <string name="COLOR_SPACE">Kleurruimte</string>
  <string name="14_BIT_RECORDING">14-bit (RAW) opname</string>
  <string name="RAW_RECORDING_BIT_MODE">Instelling opname in 12-bits RAW-formaat</string>
  <string name="NEUTRAL">Neutraal</string>
  <string name="PICTURE_CONTROL">Beeldinstelling</string>
  <string name="LOSSLESS_COMPRESSED_RAW">RAW compressie zonder kwaliteitsverlies</string>
  <string name="RAW_COMPRESSION">Raw Compressie </string>
  <!--End Property values-->
  <string name="Mode">_Modus</string>
  <string name="Iso">_Iso</string>
  <string name="ShutterSpeed">sluitertijd</string>
  <string name="Aperture">_Diafragma</string>
  <string name="WhiteBalance">_Witbalans</string>
  <string name="ExposureComp">Belichtingscompensatie</string>
  <string name="Compression">_Compressie</string>
  <string name="MeteringMode">Lichtmeting-stand</string>
  <string name="FocusMode">_Scherpstel modus</string>
  <string name="Battery">Batterij</string>
  <string name="SDRam">SD_Ram</string>
  <string name="SDRamToolTip">Afbeeldingen direct op de computer opslaan.</string>
  <string name="CapturePhotoToolTip">Foto maken</string>
  <string name="CapturePhotoNoAfToolTip">Foto maken zonder auto focus</string>
  <string name="BraketingToolTip">Bracketing (Belichting, Flits of Witbalans) reeks </string>
  <string name="SettingsToolTip">Instellingen</string>
  <string name="TimeLapseToolTip">Time-Lapse</string>
  <string name="FullscreenToolTip">Volledig scherm</string>
  <string name="LiveViewToolTip">Live beeld</string>
  <string name="BrowseSessionsToolTip">Blader door sessies</string>
  <string name="SelectTagsToolTip">Selecteer Labels</string>
  <string name="AboutToolTip">Over</string>
  <string name="Session">Sessie</string>
  <string name="SessionAdd">Toevoegen</string>
  <string name="SessionEdit">Bewerken</string>
  <string name="SessionDel">Verwijder</string>
  <string name="MainWindowTitle">NCC - Vertaald</string>
  <string name="SettingsWindowTitle">Instellingen</string>
  <string name="SessionWindowTitle">Sessie  [toevoegen/bewerken]</string>
  <string name="LiveViewWindowTitle">Livebeeld</string>
  <string name="PresetEditWindowTitle">Instelling aanpassen</string>
  <string name="BraketingWindowTitle">Braketing</string>
  <string name="EditTagWindowTitle">Label [toevoegen/bewerken]</string>
  <string name="MultipleCameraWindowTitle">Multi-camera besturing</string>
  <string name="SavePresetWindowTitle">Vooraf ingestelde waarden opslaan</string>
  <string name="TimeLapseWindowTitle">Time-Lapse</string>
  <string name="ButtonOk">Ok</string>
  <string name="ButtonCancel">Annuleren</string>
  <string name="ButtonAdd">Toevoegen</string>
  <string name="ButtonDelete">Verwijderen</string>
  <string name="ButtonEdit">Bewerken</string>
  <string name="ButtonAutoFocus">Automatisch Scherpstellen</string>
  <string name="ButtonCapture">_Opname</string>
  <string name="ButtonRecordMovie">Film opnemen</string>
  <string name="ButtonFreezeImage">Beeld bevriezen</string>
  <string name="ButtonStart">Start</string>
  <string name="ButtonPreview">Voorbeeld</string>
  <string name="ButtonStop">Stop</string>
  <string name="ButtonDeletePreset">Verwijder vooraf ingestelde waarde</string>
  <string name="ButtonDeleteProperty">Verwijder eigenschap</string>
  <string name="ButtonClose">Sluiten</string>
  <string name="ButtonSave">Opslaan</string>
  <string name="ButtonCapturePhotos">Foto\'s maken</string>
  <string name="ButtonStartTimeLapse">Start tijd opnamen</string>
  <string name="ButtonStopTimeLapse">Stop tijd opnamen</string>
  <string name="ButtonCreateMovie">Film maken</string>
  <string name="ButtonLocateLogFile">Lokaliseren log-bestand</string>
  <string name="LabelInterfaceLanguage">Taalinstellingen</string>
  <string name="LabelDisableDriver">Native drivers uitschakelen (niet aan te raden)</string>
  <string name="LabelTheme">Thema:</string>
  <string name="LabelGeneral">Algemeen</string>
  <string name="LabelPreview">Voorbeeld</string>
  <string name="LabelPlaySound">Speel geluid na foto opname</string>
  <string name="LabelAutoPreview">Automatisch voorbeeld</string>
  <string name="LabelPreviewAfterCapture">Voorbeeld afbeelding na opname in volledig scherm</string>
  <string name="LabelPreviewTime">Voorbeeld tijd in sec:</string>
  <string name="LabelPreviewInLIveView">Voobeeld afbeelding na opnamen in live beeld</string>
  <string name="LabelLIveViewImageFreeze">Live beeld bevriezen in sec:</string>
  <string name="LabelRotateImage">Afbeelding roteren:</string>
  <string name="LabelDontLoadThumbs">Geen miniaturen laden</string>
  <string name="LabelFullscrenBack">Volledig scherm achtergrond:</string>
  <string name="LabelTriggers">Triggers</string>
  <string name="LabelUseKeybordToTrigger">Gebruik toetsenbord als trigger bij het maken van foto</string>
  <string name="LabelWebserver">Webserver</string>
  <string name="LabelUseWebserver">Gebruik webserver</string>
  <string name="LabelFocusAndLiveview">Scherpstellen en live beeld</string>
  <string name="LabelSmallFocusSstep">Kleine scherpstel stap</string>
  <string name="LabelMediumFocusStep">Gemiddelde scherpstel stap</string>
  <string name="LabelLargFocusStep">Grote scherpstel stap</string>
  <string name="ReStartToolTip">U moet de applciation afsluiten en opnieuw opstarten om de wijzigingen door te voeren.</string>
  <string name="LabelSessonName">Sessie naam:</string>
  <string name="LabelFolder">Map:</string>
  <string name="LabelFileNameTemplate">Bestandsnaam Template:</string>
  <string name="LabelFileNameTemplateToolTip">$N - Sessie naam\n$C - Teller\n$E - Belichtings correctie\n$X - Camera naam\n$D - Actuele datum\n$UTime - Unix tijdnotatie\n$Type - Bestandstype (RAW|Jpg)\n$B - Streepjescode\n$Tag1 - Geselecteerde label 1\n$Tag2 - Geselecteerde label 2\n$Tag3 - Geselecteerde tabel 3\n$Tag4 - Geselecteerde tabel 4</string>
  <string name="LabelCounter">Teller:</string>
  <string name="LabelUseOriginal">Gebruik originele camera bestandsnaam</string>
  <string name="LabelUseOriginalToolTip">De optie werkt niet via de WIA driver</string>
  <string name="LabelDontDownloadPhotos">Geen foto\'s verzenden naar de PC</string>
  <string name="LabelAlowFolderChange">Toestaan om map te veranderen bij gebruik van afbeelding verkenner</string>
  <string name="LabelTags">Tags</string>
  <string name="LabelManualFocus">Handmatig scherpstellen</string>
  <string name="LabelGrid">Raster</string>
  <string name="LabelLvZoomRation">Lv zoom ratio</string>
  <string name="LabelFocusStacking">Focus Stacking</string>
  <string name="LabelNoOfPhots">Aantal foto\'s</string>
  <string name="LabelFocusStep">Scherpstel stap</string>
  <string name="LabelLuminosity">Helderheid</string>
  <string name="LabelExposureBracketing">Belichtings bracketing</string>
  <string name="LabelExposureBracketingToolTip">Zet de camera in Aperture (A) mode en schakel Automatische ISO en Automatische Witbalans uit voor het verkrijgen van de meest betrouwbare resultaten</string>
  <string name="LabelManualExposureBracketing">Handmatige belichtings bracketing</string>
  <string name="LabelManualExposureBracketingToolTip">Zet de camera in de Manual (M) mode en schakel Automatische ISO en Automatische Witbalans uit voor het verkrijgen van de meest betrouwbare resultaten.  </string>
  <string name="LabelPresetBracketing">Instelling bracketing</string>
  <string name="LabelTagDisplayValue">Toon Waarde</string>
  <string name="LabelTagValue">Waarde</string>
  <string name="LabelTagIncludeInGroup1">Voeg toe aan groep 1</string>
  <string name="LabelTagIncludeInGroup2">Voeg toe aan groep 2</string>
  <string name="LabelTagIncludeInGroup3">Voeg toe aan groep 3</string>
  <string name="LabelTagIncludeInGroup4">Voeg toe aan groep 4</string>
  <string name="LabelDelay">Vertraging (msec)</string>
  <string name="LabelNumberOfCaptures">Aantal opnamen</string>
  <string name="LabelWaitTime">Wachttijd (sec)</string>
  <string name="LabelDisableAutofocus">Automatisch scherpstellen uitschakelen</string>
  <string name="LabelConnectedCameras">Aangesloten camera\'s</string>
  <string name="LabelPresetName">Naam instelling</string>
  <string name="LabelTimeLapse">Time-Lapse</string>
  <string name="LabelSecondsBetweenShots">Seconden tussen opnamen</string>
  <string name="LabelNumberOfPhotos">Aantal foto\'s</string>
  <string name="LabelDontAutofocusOnEveryCapture">Niet automatisch scherpstellen tussen opnamen</string>
  <string name="LabelCaptureInterval">Opname interval (HH:MM:SS)</string>
  <string name="LabelMovieLenght">FIlm lengte (HH:MM:SS)</string>
  <string name="LabelMovieSettings">Film instellingen</string>
  <string name="LabelVideoFormat">Video formaat</string>
  <string name="LabelOutputFile">Output bestand</string>
  <string name="LabelFps">Bps</string>
  <string name="LabelFillImage">Afbeelding vullen</string>
  <string name="LabelCreateMovie">Film maken</string>
  <string name="LabelAddVirtualMovingToVideo">Virtuele beweging toevoegen aan video</string>
  <string name="LabelMovingSurface">Oppervlak bewegen (%):</string>
  <string name="LabelMovingDirection">Bewegingsrichting</string>
  <string name="LabelMovingDirectionLeftToRight">Links naar rechts</string>
  <string name="LabelMovingDirectionRightToLeft">Rechts naar links</string>
  <string name="LabelMovingDirectionTopToBottom">Boven naar beneden</string>
  <string name="LabelMovingDirectionBottomToTop">Beneden naar boven</string>
  <string name="LabelMovingDirectionLeftTopToRightBottom">Linksboven naar rechtsonder</string>
  <string name="LabelMovingDirectionRightBottomToLeftTop">Rechtsonder naar linksboven</string>
  <string name="LabelImageAlignment">Afbeeldingsrichting</string>
  <string name="LabelImageAlignmentLeftTop">Links/boven</string>
  <string name="LabelImageAlignmentCenter">Midden</string>
  <string name="LabelImageAlignmentRightBottom">Rechts/Onder</string>
  <string name="LabelVideoCodecProblem">Video codec probleem</string>
  <string name="MsgPhotoTransferBegin">Begin foto overdracht</string>
  <string name="MsgPhotoTransferDone">Foto overdracht uitgevoerd</string>
  <string name="MsgPhotoTransferError">Overdracht fout !⏎ Melding :{0}</string>
  <string name="MsgBulbModeNotSupported">Bulb-modus niet ondersteund!</string>
  <string name="MsgApplicationUpToDate">Dit programma is bijgewerkt!</string>
  <string name="MsgUseSessionEditorTags">Gebruik de sessie editor om de tags te definiëren!</string>
  <string name="MsgLastSessionCantBeDeleted">Laatste sessie kan niet worden verwijderd</string>
  <string name="MsgStopTimeLapse">De time-lapse is niet beëindigd! Wilt u de time-lapse afbreken?</string>
  <string name="MsgInstallXvidCodec">Xvid codec niet geïnstalleerd!⏎ Wilt u deze downloaden en installeren?</string>
  <string name="MsgDeleteSessionQuestion">Wilt U doorgaan met het verwijderen van sessie {0} ?⏎ Er worden geen bestanden gewist!</string>
  <string name="MsgBracketingDone">Bracketing uitgevoerd</string>
  <string name="MsgActionInProgress">Actie wordt uitgevoerd {0}/{1}</string>
  <string name="MenuFile">_Bestand</string>
  <string name="MenuReScan">Re-scan aangesloten camera\'s</string>
  <string name="MenuConnectedCameras">Aangesloten camera\'s</string>
  <string name="MenuExit">Afsluiten</string>
  <string name="MenuView">_Bekijken</string>
  <string name="MenuMultipleCamera">Meervoudige camera besturing</string>
  <string name="MenuSelectedCameraProperty">Geselecteerde camera eigenschap</string>
  <string name="MenuPresets">Instellingen</string>
  <string name="MenuPresetsLoad">Laden</string>
  <string name="MenuPresetsSave">Opslaan</string>
  <string name="MenuPresetsEdit">Bewerken</string>
  <string name="MenuHelp">_Help</string>
  <string name="MenuHomePage">Homepagina</string>
  <string name="MenuCheckForUpdate">Controleer op updates</string>
  <string name="MenuDonate">Doneer</string>
  <string name="MenuAbout">Over</string>
  <string name="MenuLayout">Layout</string>
  <string name="MenuLayoutNormal">Normaal</string>
  <string name="MenuLayoutGridRight">Raster rechts</string>
  <string name="MenuLayoutGrid">Grid</string>
  <string name="MenuProperties">Eigenschappen</string>
  <string name="MenuUseSelectedCameraPreset">Gebruik geselecteerde camera preset</string>
  <!--15/10/2012-->
  <string name="LabelExternalViewerPath">Context-menu externe viewer</string>
  <string name="LabelStayOnTop">Altijd bovenaan</string>
  <!--22/10/2012-->
  <string name="LabelDisplay">Toon</string>
  <string name="LabelMotionDetection">Bewegingsdetectie</string>
  <string name="LabelActivateMotionDetection">Activeer bewegingsdetectie</string>
  <string name="LabelCaptureWhenMove">Opname bij bewegingsdetectie</string>
  <string name="LabelThreshold">Drempelwaarde (%)</string>
  <string name="LabelWaitMoion">Wacht (sec)</string>
  <!--25/10/2012-->
  <string name="LabelAutofocusBeforeCapture">Automatisch scherpstellen voor opname</string>
  <!--26/10/2012-->
  <string name="LabelOpacity">Opaciteit</string>
  <!--29/10/2012-->
  <string name="LabelMotionDetectionType">Bewegingsdetectie type</string>
  <string name="LabelTwoFramesDifferenceDetector">Twee-Frame verschil-detector</string>
  <string name="LabelSimpleBackgroundModelingDetector">Eenvoudige Background-Modeling detector</string>
  <string name="LabelSmallestBlockSize">Kleinste datablok grootte</string>
  <string name="ButtonHelp">Help</string>
  <!--31/10/2012-->
  <string name="LabelMenu">Menu</string>
  <!--03/11/2012-->
  <string name="MenuForum">Forum</string>
  <!--07/11/2012-->
  <string name="ButtonGetRawCodec">Verkrijg de raw codec</string>
  <!--08/11/2012-->
  <string name="LabelErrorRecordMovie">Fout bij starten filmopname</string>
  <string name="LabelNoCardInserted">Geen Geheugenkaart aanwezig</string>
  <string name="LabelCardError">Geheugenkaart Fout</string>
  <string name="LabelCardNotFormatted">Geheugenkaart niet geformatteerd</string>
  <string name="LabelNoFreeAreaInCard">Geen vrije ruimte op geheugenkaart</string>
  <string name="LabelCardBufferNotEmpty">Er is geen data in de buffer die weggeschreven gaat worden in een geheugenkaart.</string>
  <string name="LabelPcBufferNotEmpty">Er is geen data in de buffer dat weggeschreven gaat worden in het PC geheugen.</string>
  <string name="LabelBufferNotEmpty">Er is geen film data in de buffer aanwezig.</string>
  <string name="LabelRecordInProgres">Tijdens filmopname</string>
  <string name="LabelCardProtected">Geheugenkaart beschermd</string>
  <string name="LabelDuringEnlargedDisplayLiveView">Tijdens vergroten van het Live-view venster</string>
  <string name="LabelWrongLiveViewType">De set Live-view selector is in de Live-view fotografie.</string>
  <string name="LabelNotInApplicationMode">De camera is niet in de applicatie mode.</string>
  <string name="ButtonResetSettings">Instellingen resetten</string>
  <!--14/11/2012-->
  <string name="LabelUseExternalViewer">Gebruik externe viewer</string>
  <string name="LabelExternalPreViewerPath">Externe viewer bestandslokatie</string>
  <string name="LabelExternalPreViewerArgs">Exterene viewer argumenten</string>
  <!--18/11/2012-->
  <string name="LabelControl">Besturing</string>
  <!--20/11/2012-->
  <string name="LabelExport">Exporteer</string>
  <!--21/11/2012-->
  <string name="LabelDownload">Download</string>
  <!--25/11/2012-->
  <string name="DownloadWindowTitle">Download foto\'s</string>
  <string name="LabelDeleteFilesAfterTransfer">Verwijder bestanden na overdracht</string>
  <string name="LabelAskForDelete">Overgedragen bestanden zullen worden verwijderd.\nWil je verder gaan?</string>
  <!--26/11/2012-->
  <string name="LabelErrorSetFocusPos">Fout bij instelling focus positie</string>
  <string name="LabelErrorUnableFocus">Scherpstellen niet mogelijk</string>
  <!--28/11/2012-->
  <string name="LabelErrorLoadingFileList">Fout bij laden bestandslijst</string>
  <!--30/11/2012-->
  <string name="LabelTransfer">Transfer</string>
  <string name="LabelTransferItem1">1.Opslaan enkel op PC</string>
  <string name="LabelTransferItem2">2.Opslaan enkel op camera</string>
  <string name="LabelTransferItem3">3.Opslaan op PC en camera</string>
  <!--05/12/2012-->
  <string name="MsgDisabledDrivers">Native drivers zijn uitgeschakeld! Wilt U dat ze worden ingeschakeld?</string>
  <!--14/12/2012-->
  <string name="LabelShowFocusPoints">Toon focuspunten</string>
  <string name="LabelMainWindow">Hoofdvenster</string>
  <string name="LabelSelect">Selecteer</string>
  <string name="TimeSelectWindowTitle">Selecteer venster</string>
  <!--16/12/2012-->
  <string name="LabelRotateNone">Geen</string>
  <string name="LabelRotate90">Roteer 90</string>
  <string name="LabelRotate180">Roteer 180</string>
  <string name="LabelRotate270">Roteer 270</string>
  <string name="LabelLowMemoryUsage">Laag geheugengebruik</string>
  <!--04/01/2013-->
  <string name="LabelRawCodecNotInstalled">Raw codec niet geïnstalleerd  of onbekend bestandsformaat</string>
  <!--05/01/2013-->
  <string name="LabelUseCameraCounter">Gebruik de camera-teller in plaats van de generieke teller</string>
  <string name="LabelResetCounters">Reset teller</string>
  <!--07/01/2013-->
  <string name="LabelUnabletoDeleteSession">Kan sessie niet verwijderen</string>
  <!--12/01/2013-->
  <string name="LabelWaitingForDevice">Wachten op het beschikbaar zijn van het apparaat</string>
  <string name="LabelAdvanced">Geavanceerd</string>
  <string name="LabelUseParellelTransfer">Gebruik parallele bestandsoverdracht</string>
  <!--19/01/2013-->
  <string name="LabelUnHandledError">Een programmafout is opgetreden.⏎ Controleer of uw data correct is en herhaal de actie. Als de fout blijft optreden dan is dit waarschijnlijk het gevolg van een ernstige storing in het programma en kunt U het beter afsluiten.⏎ ⏎ Error:{0}⏎ ⏎ Wilt U doorgaan?⏎ (Als U Ja kiest dan kunt U door gaan met U werk, Kiest U Nee dan wordt het programma afgesloten)</string>
  <string name="LabelApplicationError">Applicatie fout</string>
  <string name="LabelWiaNotInstalled">WIA 2.0 is niet geïnstalleerd</string>
  <string name="LabelRestartTheApplication">Herstart het programma!</string>
  <string name="LabelOutOfMemory">Het programma heeft te weinig geheugen ter beschikking en wordt afgesloten!</string>
  <string name="LabelApplicationAlreadyRunning">Toepassing reeds geopend</string>
  <string name="LabelDeleteSession">Verwijder sessie</string>
  <string name="LabelStartCapture">Start opname</string>
  <string name="LabelStopCapture">Stop opname</string>
  <string name="LabelCaptureTime">Opname tijd (sec)</string>
  <string name="LabelTimeBetweenShots">Tijd tussen de verschillende opnames</string>
  <string name="LabelDontAutofocus">Geen autofocus</string>
  <string name="LabelShowUnTranslatedStringIds">Geef onvertaalde string ids weer</string>
  <!--20/01/2013-->
  <string name="LabelUseAsMaster">Gebruik als master</string>
  <!--29/01/2013-->
  <string name="LabelCounterIncrementer">Marge waarmee de bestandsnummering stapsgewijs wordt verhoogd.</string>
  <string name="LabelSelected">Geselecteerd</string>
  <!--31/01/2013-->
  <string name="LabelNone">Geen</string>
  <string name="LabelRuleOfThirds">Regel van derden</string>
  <string name="LabelComboGrid">Grid</string>
  <string name="LabelDiagonal">Diagonaal</string>
  <string name="LabelSplit">Splis</string>
  <!--13/03/2013-->
  <string name="LabelTools">Gereedschappen</string>
  <!--17/03/2012-->
  <string name="LabelMFError">Camera is in handmatige focus mode</string>
  <string name="LabelNotAFSError">Camera is in Auto-Focus mode</string>
  <!--28/03/2012-->
  <string name="LabelSequenceError">Fout in de sequentie.</string>
  <string name="LabelFullyPressedButtonError">Fout: Druk de ontspanknop helemaal in.</string>
  <string name="LabelApertureValueError">De diafragmawaarde wordt ingesteld met de diafragmaring van het objectief.</string>
  <string name="LabelBulbError">Bulb fout</string>
  <string name="LabelDuringCleaningMirror">Tijdens reinigingsactiviteit spiegel omhoog.</string>
  <string name="LabelDuringInsufficiencyBattery">Bij onvoldoende laadniveau van batterij</string>
  <string name="LabelTTLError">TTL fout</string>
  <string name="LabelNonCPULEnseError">Er is een niet-CPU objectief aangebracht en de diafragmavoorkeuze is niet ingesteld op M.</string>
  <string name="LabelImageInRAM">Er is een afbeelding met de opnamebestemming SDRAM.</string>
  <string name="LabelNoCardInsertedError">De bestemming van de opname is de geheugenkaart of de kaart en het SDRAM-geheugen,\nen de kaart is niet geplaatst terwijl de modus is uitgeschakeld zonder een kaart.</string>
  <string name="LabelCommandProcesingError">Tijdens de verwerking van het opnamecommando</string>
  <string name="LabelShoutingInProgress">De programmakeuze is EFFECTEN.</string>
  <string name="LabelOverHeatedError">De Livebeeld modus kan niet gebruikt worden bij te hoge temperaturen.</string>
  <string name="LabelCardProtectedError">Gegevens op Geheugenkaart zijn beveiligd.</string>
  <string name="LabelMirrorUpError">De camera is ingesteld op Spiegel-omhoog en de spiegel-omhoog modus wordt uitgevoerd.</string>
  <string name="LabelMirrorUpError2">De opname stand is [Mirror-up]  </string>
  <string name="LabelDestinationCardError">De opnamebestemming is de geheugenkaart.</string>
  <string name="LabelLiveViewError">Fout bij starten Livebeeld.</string>
  <!--07/05/2013-->
  <string name="LabelDevices">Apparaten</string>
  <string name="LabelExternalShutterRelease">Vanaf afstand bediende ontspanner.</string>
  <string name="LabelConfigName">configuratienaam</string>
  <string name="LabelDriver">Stuurprogramma</string>
  <string name="LabelAstronomy">Astronomie</string>
  <string name="LabelEnable">inschakelen</string>
  <string name="LabelUseConfiguration">Gebruik configuratie</string>
  <string name="LabelNoExternalDeviceSelected">Geen extern apparaat is geselecteerd</string>
  <string name="LabelScript">Draaiboek</string>
  <string name="LabelStartScript">Start draaiboek</string>
  <string name="LabelDeviceSettings">Apparaatinstellingen</string>
  <string name="LabelAvailableDevices">Beschikbare apparaten</string>
  <string name="LabelCommands">Opdrachten</string>
  <string name="LabelStartLiveView">Start Livebeeld</string>
  <string name="LabelStopLiveView">Stop Livebeeld</string>
  <string name="LabelBrightness">Helderheid</string>
  <string name="LabelUseExternalShutterRelease">Gebruik afstandsbediening ontspanner.</string>
  <string name="LabelDownloadJpgOnly">Download alleen Jpg file</string>
  <string name="LabelDownloadJpgOnlyToolTip">Als opname gemaakt is met JPG + RAW worden alleen de JPG bestanden gedownload</string>
  <string name="LabelSetCounters">Stel bestandsnummering in.</string>
  <string name="LabelEdgeDetection">Edge detectie</string>
  <!--04/07/2013-->
  <string name="LabelShowFocusRect">Focus rechthoek weergeven</string>
  <string name="LabelExif">Extra Informatie Foto (Metagegevens)</string>
  <string name="LabelImageProperties">Eigenschappen Afbeelding</string>
  <string name="LabelFileName">Bestandsnaam</string>
  <string name="LabelTagSelector">Label selector</string>
  <string name="LabelComment">Opmerking</string>
  <string name="LabelWriteComments">Schrijf opmerkingen/labels in gedownload afbeeldingsbestand</string>
  <string name="LabelStayOnTop2">Blijf bovenaan</string>
  <string name="LabelWriteSelectedTags">Neem labels over van selector</string>
  <string name="LabelClearCache">Wis tussengeheugen</string>
  <string name="LabelShowMagnifierInFullSccreen">Toon zoomfunctie in volbeeldmodus</string>
  <string name="LabelDelayImageLoading">Vertraging beeldopbouw</string>
  <string name="LabelPHDGuiding">Push Here Dummy Guiding</string>
  <string name="LabelWaitPHDGuiding">Wachten op PHD (sec)</string>
  <string name="LabelCountDown">Aftellen</string>
  <string name="LabelRemainingCaptures">resterende Opnamen</string>
  <string name="LabelLiveViewRotation">Live beeld rotatie</string>
  <string name="LabelAutoRotate">Auto rotatie</string>
  <string name="LabelReset">Resetten</string>
  <string name="LabelFocus">Focus</string>
  <!--17/11/2013-->
  <string name="LabelBarcode">Barcode</string>
  <string name="LabelSendTheLogFile">Stuur logboekbestand</string>
  <string name="LabelAskSendLogFile">Wilt u het logboekbestand naar de ontwikkelaars sturen ?</string>
  <string name="LabelSyncCameraDate">Synchroniseer camera datum/tijd op aangesloten camera</string>
  <string name="LabelShowThumbUpDown">Toon miniaturen op/neer knoppen.</string>
  <string name="LabelSend">Zenden</string>
  <string name="LabelLogMessage">Bericht aan de ontwikkelaars van digiCamControl :</string>
  <string name="LabelLogText">Het logboekbestand zal naar het digiCamControl ontwikkelingsteam gezonden worden om de toepassingsstabiliteit te verbeteren.</string>
  <string name="LabelFullscreen">Volledig scherm</string>
  <string name="LabelSelection">Selectie</string>
  <string name="LabelSelectAll">Selecteer Alles</string>
  <string name="LabelSelectNone">Niets Selecteren</string>
  <string name="LabelSelectLiked">Selecteer Liked</string>
  <string name="LabelSelectUnLiked">Selecteer Unliked</string>
</resources>
